{"id":882709,"xmlId":"org.jetbrains.plugins.vue","name":"Vue.js","description":"<p>Provides <a href=\"https://vuejs.org/\">Vue.js</a> support to all JetBrains IDEs that\n    <a href=\"https://www.jetbrains.com/products/#lang=js&amp;type=ide\">support JavaScript</a>.</p>\n\n    <h2>Features</h2>\n    <ul>\n      <li>Completion of components, directives, props, and methods in templates</li>\n      <li>Navigation from the component, directives, and event handlers to their definition</li>\n      <li>Coding assistance for different languages inside the template, script, and style tags in <code>.vue</code> files</li>\n      <li>Extract component and rename component refactorings</li>\n      <li>Collection of code snippets for Vue.js</li>\n      <li>New Vue project option in the <i>Welcome</i> screen</li>\n    </ul>\n\n    <h2>Getting started</h2>\n    <p>For information on getting started, head over to the <a href=\"https://www.jetbrains.com/help/\">documentation</a> for your IDE.\n    For WebStorm, you can check out this section in the <a href=\"https://www.jetbrains.com/help/webstorm/vue-js.html\">documentation</a>.</p>\n<h2>Getting started</h2>\n<p>Support includes:</p> \r\n<ul> \r\n <li>Code completion in the script, style and template blocks in .vue files (supported languages include: ES6, TypeScript, HTML, Pug, CSS, Sass, SCSS, Less).</li> \r\n <li>Support for the Vue template syntax.</li> \r\n</ul>","organization":"JetBrains s.r.o.","tags":["Framework"],"version":"252.27397.112","dependencies":["com.intellij.css","intellij.spellchecker","intellij.webpack","com.intellij.modules.xml","JavaScript","org.intellij.plugins.postcss"],"optionalDependencies":["org.intellij.plugins.markdown","intellij.prettierJS","com.intellij.copyright","JavaScriptDebugger"],"since":"252.27397","until":"252.*","size":3292533,"vendor":"JetBrains","sourceCodeUrl":"https://github.com/JetBrains/intellij-plugins/tree/master/vuejs"}